
{
  "tables": [
    {
      "name": "SalesData",
      "columns": [
        { "name": "data", "dataType": "dateTime" },
        { "name": "venda", "dataType": "int64" },
        { "name": "estoque", "dataType": "int64" },
        { "name": "preco", "dataType": "double" },
        { "name": "year", "dataType": "int64" },
        { "name": "month", "dataType": "int64" },
        { "name": "day", "dataType": "int64" },
        { "name": "weekday", "dataType": "string" },
        { "name": "venda_7day_avg", "dataType": "double" },
        { "name": "category", "dataType": "string" },
        { "name": "store", "dataType": "string" },
        { "name": "region", "dataType": "string" }
      ],
      "measures": [
        { "name": "Total Sales", "expression": "SUM(SalesData[venda])" },
        { "name": "Avg Sales", "expression": "AVERAGE(SalesData[venda])" },
        { "name": "Low Stock Alerts", "expression": "COUNTROWS(FILTER(SalesData, SalesData[estoque] < 50))" }
      ]
    }
  ]
}